vultr/conf.py
vultr/version.py
vultr/acct/vultr/auth.py
vultr/exec/vultr/account.py
vultr/exec/vultr/api_key.py
vultr/exec/vultr/application.py
vultr/exec/vultr/backup.py
vultr/exec/vultr/block_storage.py
vultr/exec/vultr/init.py
vultr/exec/vultr/iso_image.py
vultr/exec/vultr/network.py
vultr/exec/vultr/operating_system.py
vultr/exec/vultr/plans.py
vultr/exec/vultr/regions.py
vultr/exec/vultr/reserved_ip.py
vultr/exec/vultr/snapshot.py
vultr/exec/vultr/ssh_key.py
vultr/exec/vultr/startup_script.py
vultr/exec/vultr/user_management.py
vultr/exec/vultr/util.py
vultr/exec/vultr/baremetal/app.py
vultr/exec/vultr/baremetal/ipv4.py
vultr/exec/vultr/baremetal/ipv6.py
vultr/exec/vultr/baremetal/os_change.py
vultr/exec/vultr/baremetal/server.py
vultr/exec/vultr/baremetal/user.py
vultr/exec/vultr/baremetal/contracts/init.py
vultr/exec/vultr/contracts/init.py
vultr/exec/vultr/contracts/util.py
vultr/exec/vultr/dns/dnssec.py
vultr/exec/vultr/dns/domain.py
vultr/exec/vultr/dns/record.py
vultr/exec/vultr/dns/soa.py
vultr/exec/vultr/firewall/group.py
vultr/exec/vultr/firewall/rule.py
vultr/exec/vultr/loadbalancer/config.py
vultr/exec/vultr/loadbalancer/forward_rule.py
vultr/exec/vultr/loadbalancer/generic.py
vultr/exec/vultr/loadbalancer/health_check.py
vultr/exec/vultr/loadbalancer/instance.py
vultr/exec/vultr/loadbalancer/ssl.py
vultr/exec/vultr/loadbalancer/subscription.py
vultr/exec/vultr/loadbalancer/contracts/init.py
vultr/exec/vultr/object_storage/cluster.py
vultr/exec/vultr/object_storage/subscription.py
vultr/exec/vultr/object_storage/contracts/init.py
vultr/exec/vultr/server/app.py
vultr/exec/vultr/server/backup.py
vultr/exec/vultr/server/ipv4.py
vultr/exec/vultr/server/ipv6.py
vultr/exec/vultr/server/iso.py
vultr/exec/vultr/server/os_change.py
vultr/exec/vultr/server/private_network.py
vultr/exec/vultr/server/upgrade_plan.py
vultr/exec/vultr/server/user.py
vultr/exec/vultr/server/virtual_machine.py
vultr/exec/vultr/server/contracts/init.py
idem_vultr-1.5.dist-info/METADATA
idem_vultr-1.5.dist-info/WHEEL
idem_vultr-1.5.dist-info/top_level.txt
idem_vultr-1.5.dist-info/RECORD
