Metadata-Version: 2.1
Name: idem-vultr
Version: 1.5
Summary: States and execution modules for the vultr cloud provider
Home-page: https://gitlab.com/saltstack/pop/idem-vultr
Author: Tyler Johnson
Author-email: tjohnson@saltstack.com
License: UNKNOWN
Platform: UNKNOWN
Classifier: Operating System :: OS Independent
Classifier: Programming Language :: Python
Classifier: Programming Language :: Python :: 3.6
Classifier: Programming Language :: Python :: 3.7
Classifier: Programming Language :: Python :: 3.8
Classifier: Development Status :: 5 - Production/Stable
Requires-Python: >=3.6
Requires-Dist: acct (>=1.5)
Requires-Dist: dict-toolbox (>=1.5)
Requires-Dist: idem (>=7.1)
Requires-Dist: pop (>=13)
Requires-Dist: pop-config (>=6.2)
Requires-Dist: httpx (>=0.13.0)
